{
  "key": "group_69369efd6948d",
  "title": "Product",
  "fields": [
    {
      "key": "field_69369f1477d1f",
      "label": "Description",
      "name": "description",
      "aria-label": "",
      "type": "wysiwyg",
      "instructions": "",
      "required": 0,
      "conditional_logic": 0,
      "wrapper": {
        "width": "",
        "class": "",
        "id": ""
      },
      "default_value": "",
      "allow_in_bindings": 0,
      "tabs": "all",
      "toolbar": "full",
      "media_upload": 1,
      "delay": 0
    },
    {
      "key": "field_69369f1d77d20",
      "label": "Brand Name",
      "name": "brand_name",
      "aria-label": "",
      "type": "text",
      "instructions": "",
      "required": 0,
      "conditional_logic": 0,
      "wrapper": {
        "width": "",
        "class": "",
        "id": ""
      },
      "default_value": "",
      "maxlength": "",
      "allow_in_bindings": 0,
      "placeholder": "",
      "prepend": "",
      "append": ""
    },
    {
      "key": "field_69369f3677d21",
      "label": "Material",
      "name": "material",
      "aria-label": "",
      "type": "select",
      "instructions": "",
      "required": 0,
      "conditional_logic": 0,
      "wrapper": {
        "width": "",
        "class": "",
        "id": ""
      },
      "choices": {
        "HDPE": "HDPE",
        "Kraft": "Kraft",
        "rPET": "rPET",
        "PP": "PP",
        "R\/Paper": "R\/Paper",
        "Pulp": "Pulp",
        "LLDPE": "LLDPE",
        "HD": "HD"
      },
      "default_value": false,
      "return_format": "value",
      "multiple": 0,
      "allow_null": 0,
      "allow_in_bindings": 0,
      "ui": 0,
      "ajax": 0,
      "placeholder": "",
      "create_options": 0,
      "save_options": 0
    },
    {
      "key": "field_69369f8877d22",
      "label": "Size",
      "name": "size",
      "aria-label": "",
      "type": "text",
      "instructions": "",
      "required": 0,
      "conditional_logic": 0,
      "wrapper": {
        "width": "",
        "class": "",
        "id": ""
      },
      "default_value": "",
      "maxlength": "",
      "allow_in_bindings": 0,
      "placeholder": "",
      "prepend": "",
      "append": ""
    },
    {
      "key": "field_6936b6c3a2c94",
      "label": "Size Units",
      "name": "size_units",
      "aria-label": "",
      "type": "text",
      "instructions": "",
      "required": 0,
      "conditional_logic": 0,
      "wrapper": {
        "width": "",
        "class": "",
        "id": ""
      },
      "default_value": "",
      "maxlength": "",
      "allow_in_bindings": 0,
      "placeholder": "",
      "prepend": "",
      "append": ""
    },
    {
      "key": "field_69369f9777d23",
      "label": "Micron",
      "name": "micron",
      "aria-label": "",
      "type": "number",
      "instructions": "",
      "required": 0,
      "conditional_logic": 0,
      "wrapper": {
        "width": "",
        "class": "",
        "id": ""
      },
      "default_value": "",
      "min": "",
      "max": "",
      "allow_in_bindings": 0,
      "placeholder": "",
      "step": "",
      "prepend": "",
      "append": ""
    },
    {
      "key": "field_69369fa277d24",
      "label": "GSM",
      "name": "gsm",
      "aria-label": "",
      "type": "number",
      "instructions": "",
      "required": 0,
      "conditional_logic": 0,
      "wrapper": {
        "width": "",
        "class": "",
        "id": ""
      },
      "default_value": "",
      "min": "",
      "max": "",
      "allow_in_bindings": 0,
      "placeholder": "",
      "step": "",
      "prepend": "",
      "append": ""
    },
    {
      "key": "field_69369fb077d25",
      "label": "Colour",
      "name": "colour",
      "aria-label": "",
      "type": "text",
      "instructions": "",
      "required": 0,
      "conditional_logic": 0,
      "wrapper": {
        "width": "",
        "class": "",
        "id": ""
      },
      "default_value": "",
      "maxlength": "",
      "allow_in_bindings": 0,
      "placeholder": "",
      "prepend": "",
      "append": ""
    },
    {
      "key": "field_6936a01277d26",
      "label": "Units of Measure",
      "name": "uom",
      "aria-label": "",
      "type": "text",
      "instructions": "",
      "required": 0,
      "conditional_logic": 0,
      "wrapper": {
        "width": "",
        "class": "",
        "id": ""
      },
      "default_value": "",
      "maxlength": "",
      "allow_in_bindings": 0,
      "placeholder": "",
      "prepend": "",
      "append": ""
    },
    {
      "key": "field_6936a04e77d27",
      "label": "Pack Size",
      "name": "pack_size",
      "aria-label": "",
      "type": "text",
      "instructions": "",
      "required": 0,
      "conditional_logic": 0,
      "wrapper": {
        "width": "",
        "class": "",
        "id": ""
      },
      "default_value": "",
      "maxlength": "",
      "allow_in_bindings": 0,
      "placeholder": "",
      "prepend": "",
      "append": ""
    },
    {
      "key": "field_6936a05b77d28",
      "label": "Packs per Case",
      "name": "packs_per_case",
      "aria-label": "",
      "type": "number",
      "instructions": "",
      "required": 0,
      "conditional_logic": 0,
      "wrapper": {
        "width": "",
        "class": "",
        "id": ""
      },
      "default_value": "",
      "min": "",
      "max": "",
      "allow_in_bindings": 0,
      "placeholder": "",
      "step": "",
      "prepend": "",
      "append": ""
    },
    {
      "key": "field_6936a06a77d29",
      "label": "Cases per Pallet",
      "name": "cases_per_pallet",
      "aria-label": "",
      "type": "number",
      "instructions": "",
      "required": 0,
      "conditional_logic": 0,
      "wrapper": {
        "width": "",
        "class": "",
        "id": ""
      },
      "default_value": "",
      "min": "",
      "max": "",
      "allow_in_bindings": 0,
      "placeholder": "",
      "step": "",
      "prepend": "",
      "append": ""
    },
    {
      "key": "field_lc_product_compartments",
      "label": "Compartments",
      "name": "compartments",
      "aria-label": "",
      "type": "number",
      "instructions": "",
      "required": 0,
      "conditional_logic": 0,
      "wrapper": {
        "width": "25",
        "class": "",
        "id": ""
      },
      "default_value": "",
      "min": "",
      "max": "",
      "allow_in_bindings": 0,
      "placeholder": "",
      "step": "",
      "prepend": "",
      "append": ""
    },
    {
      "key": "field_lc_product_close_depth",
      "label": "Close Depth",
      "name": "close_depth",
      "aria-label": "",
      "type": "number",
      "instructions": "",
      "required": 0,
      "conditional_logic": 0,
      "wrapper": {
        "width": "25",
        "class": "",
        "id": ""
      },
      "default_value": "",
      "min": "",
      "max": "",
      "allow_in_bindings": 0,
      "placeholder": "",
      "step": "",
      "prepend": "",
      "append": ""
    },
    {
      "key": "field_lc_product_weight_min",
      "label": "Weight Min",
      "name": "weight_min",
      "aria-label": "",
      "type": "number",
      "instructions": "",
      "required": 0,
      "conditional_logic": 0,
      "wrapper": {
        "width": "25",
        "class": "",
        "id": ""
      },
      "default_value": "",
      "min": "",
      "max": "",
      "allow_in_bindings": 0,
      "placeholder": "",
      "step": "",
      "prepend": "",
      "append": ""
    },
    {
      "key": "field_lc_product_weight_max",
      "label": "Weight Max",
      "name": "weight_max",
      "aria-label": "",
      "type": "number",
      "instructions": "",
      "required": 0,
      "conditional_logic": 0,
      "wrapper": {
        "width": "25",
        "class": "",
        "id": ""
      },
      "default_value": "",
      "min": "",
      "max": "",
      "allow_in_bindings": 0,
      "placeholder": "",
      "step": "",
      "prepend": "",
      "append": ""
    }
  ],
  "location": [
    [
      {
        "param": "post_type",
        "operator": "==",
        "value": "product"
      }
    ]
  ],
  "menu_order": 0,
  "position": "normal",
  "style": "default",
  "label_placement": "top",
  "instruction_placement": "label",
  "hide_on_screen": "",
  "active": true,
  "description": "",
  "show_in_rest": 0,
  "display_title": "",
  "modified": 1770000003
}
